cheap_repr/__init__.py
cheap_repr/utils.py
cheap_repr/version.py
cheap_repr-0.5.2.dist-info/LICENSE.txt
cheap_repr-0.5.2.dist-info/METADATA
cheap_repr-0.5.2.dist-info/WHEEL
cheap_repr-0.5.2.dist-info/top_level.txt
cheap_repr-0.5.2.dist-info/RECORD
