Metadata-Version: 2.1
Name: cheap_repr
Version: 0.5.2
Summary: Better version of repr/reprlib for short, cheap string representations.
Home-page: https://github.com/alexmojaki/cheap_repr
Author: Alex Hall
Author-email: alex.mojaki@gmail.com
License: MIT
Classifier: License :: OSI Approved :: MIT License
Classifier: Programming Language :: Python
Classifier: Programming Language :: Python :: 3.8
Classifier: Programming Language :: Python :: 3.9
Classifier: Programming Language :: Python :: 3.10
Classifier: Programming Language :: Python :: 3.11
Classifier: Programming Language :: Python :: 3.12
Classifier: Programming Language :: Python :: 3.13
License-File: LICENSE.txt
Provides-Extra: tests
Requires-Dist: pytest; extra == "tests"
Requires-Dist: pandas>=0.24.2; platform_python_implementation != "PyPy" and extra == "tests"
Requires-Dist: numpy>=1.16.3; platform_python_implementation != "PyPy" and extra == "tests"
Requires-Dist: Django; extra == "tests"
